{"id": "0x2874ee214077a2087de3211b0a78bdf3a8598eb082f76717f14fc5ff27f8e237", "title": "The French Revolution is the consecration of humanity.\"\r", "body": "The French Revolution is the consecration of humanity.\"\rThe Bishop could not refrain from murmuring:--\r\"Yes? '93!\"\rThe member of the Convention straightened himself up in his chair with an almost lugubrious solemnity, and exclaimed, so far as a dying man is capable of exclamation:--\r\"Ah, there you go; '93!\rI was expecting that word.\rA cloud had been forming for the space of fifteen hundred years; at the end of fifteen hundred years it burst.\rYou are putting the thunderbolt on its trial.\"\rThe Bishop felt, without, perhaps, confessing it, that something within him had suffered extinction.\rNevertheless, he put a good face on the matter.\rHe replied:--\r\"The judge speaks in the name of justice; the priest speaks in the name of pity, which is nothing but a more lofty justice. A thunderbolt should commit no error.\"\rAnd he added, regarding the member of the Convention steadily the while, \"Louis XVII.?\"\rThat '93 was inexorable?\"\r\"Inexorable; yes,\" said the Bishop.\r\"What think you of Marat clappi", "choices": ["yes", "no"], "start": 1639649027, "end": 1639908227, "type": "single-choice", "scores": [0, 0], "scores_total": 0, "scores_state": "pending", "scores_updated": 1639908261, "snapshot": "1639649027", "state": "closed", "author": "0xa054dD9e5a1C865192058F7135fB674d56DA5AE8", "space": {"id": "aelincouncil.eth", "name": "Aelin Protocol Council"}, "votes": 0, "votes_data": []}