{"id": "0x5227c74a6413ac5b44170ac698ac14f718a8c777381f1e63f0acffa389d489e7", "title": "The conventionary stretched forth his hand and grasped the Bishop's arm.\r", "body": "The conventionary stretched forth his hand and grasped the Bishop's arm.\r\"Louis XVII.! let us see.\rFor whom do you mourn? is it for the innocent child? very good; in that case I mourn with you. Is it for the royal child?\rI demand time for reflection. To me, the brother of Cartouche, an innocent child who was hung up by the armpits in the Place de Greve, until death ensued, for the sole crime of having been the brother of Cartouche, is no less painful than the grandson of Louis XV., an innocent child, martyred in the tower of the Temple, for the sole crime of having been grandson of Louis XV.\"\r\"Monsieur,\" said the Bishop, \"I like not this conjunction of names.\"\r\"Cartouche?\rLouis XV.? To which of the two do you object?\"\rA momentary silence ensued.\rThe Bishop almost regretted having come, and yet he felt vaguely and strangely shaken.\rThe conventionary resumed:--\r\"Ah, Monsieur Priest, you love not the crudities of the true. Christ loved them.\rHe seized a rod and cleared out the Temple. His", "choices": ["yes", "no"], "start": 1639649016, "end": 1639908216, "type": "single-choice", "scores": [0, 0], "scores_total": 0, "scores_state": "pending", "scores_updated": 1639908231, "snapshot": "1639649016", "state": "closed", "author": "0x51055B1c0f613af205824b137dF47B189a99816F", "space": {"id": "aelincouncil.eth", "name": "Aelin Protocol Council"}, "votes": 0, "votes_data": []}