{"id": "0xac5c965005bb0ef732ccbb4cd5ab266d072dc62eaebbca05e23a5372b33a0189", "title": "Are you expect the project to issue tokens", "body": "", "choices": ["Yes", "No"], "start": 1637510400, "end": 1638287940, "type": "single-choice", "scores": [0, 0], "scores_total": 0, "scores_state": "final", "scores_updated": 1638287973, "snapshot": "13658388", "state": "closed", "author": "0x15b3E20803A82E8B9189e215EDA999574Ac5138f", "space": {"id": "xinyang.eth", "name": "xinyang"}, "votes": 0, "votes_data": []}