{"id": "0x15cc09e8f0821006351839959b9650a454bb19f1bd19fbfc6cb41545c4ed8e13", "title": "Test proposal", "body": "Learning about the snapshot interface", "choices": ["We love it", "We hate it"], "start": 1639598400, "end": 1639684800, "type": "single-choice", "scores": [0, 0], "scores_total": 0, "scores_state": "final", "scores_updated": 1639684806, "snapshot": "8283451", "state": "closed", "author": "0x54e9A1aA8bC314ED3109C5915D2DC388B1D594bA", "space": {"id": "hittite.eth", "name": "Colony"}, "votes": 0, "votes_data": []}