{"id": "0x871739e47c6da81515b0dce7557a9286581bea31d4c7b08d7171e74a9e87180d", "title": "is Actor DAO  airdropping?", "body": "In order to decentralize, airdrop is recommended", "choices": ["yes", "no", "Abstention"], "start": 1637409600, "end": 1638230400, "type": "single-choice", "scores": [0, 0, 0], "scores_total": 0, "scores_state": "final", "scores_updated": 1638230425, "snapshot": "12791948", "state": "closed", "author": "0x80DBEd90837802EbB61907173dbaa12E5be99611", "space": {"id": "safeking.eth", "name": "Actor DAO"}, "votes": 0, "votes_data": []}