{"id": "0x5756baf758e3843d87ec81e13767619b1d335fdb5b14fea04ade144013dbd0f5", "title": "\u5143\u5b87\u5b99\u6700\u8981\u7684\u662f\u4ec0\u4e48\uff1f", "body": "\u666e\u901a\u97ed\u83dc\u5728\u5143\u5b87\u5b99\u54ea\u4e2a\u677f\u5757\u66f4\u6709\u673a\u4f1a", "choices": ["token", "\u6e38\u620f\u9053\u5177", "\u4e24\u8005\u90fd"], "start": 1638684000, "end": 1639195200, "type": "single-choice", "scores": [0, 0, 0], "scores_total": 0, "scores_state": "final", "scores_updated": 1639195225, "snapshot": "13744370", "state": "closed", "author": "0xaD2043f5A6d58f35CFD4eC9C73E2aBc23EaB4511", "space": {"id": "metaverse123.eth", "name": "metaverse"}, "votes": 0, "votes_data": []}