{"id": "0x613a6acd98d162385c5cf6f6ee6a0db2a3eec9e728f761e2df5da66e66ddfa43", "title": "\u4f60\u4eec\u64b8\u7a7a\u6295\u5417\uff1f", "body": "\u65e0\u8111\u64b8\uff1f", "choices": ["yes", "no"], "start": 1637985600, "end": 1638072000, "type": "single-choice", "scores": [0, 0], "scores_total": 0, "scores_state": "final", "scores_updated": 1638072028, "snapshot": "13694465", "state": "closed", "author": "0xD13939b58e97F60f13acD0B4629b5233d31019AA", "space": {"id": "dingguagua.eth", "name": "dingguagua"}, "votes": 0, "votes_data": []}