{"id": "0xca5975b7369ba1a149472343a0a4014223d0bda2a4609eaa55e1a015d811845d", "title": "TeaDAO\u80fd\u6210\u529f\u5417\uff1f", "body": "TeaDAO\u6700\u540e\u4f1a\u6210\u4e3azapper\u7684\u907f\u96be\u6240\u5417", "choices": ["\u4f1a", "\u4e0d\u4f1a"], "start": 1636862400, "end": 1638244800, "type": "single-choice", "scores": [3343.473120416457, 0], "scores_total": 3343.473120416457, "scores_state": "final", "scores_updated": 1638245431, "snapshot": "12609898", "state": "closed", "author": "0xF2f318A1288E5e089783c9D994872113413d044F", "space": {"id": "godboy.eth", "name": "TeaDAO"}, "votes": 1, "votes_data": [{"id": "0xeb447f7dcf570c6518c55b5326599a64139ca5ed687420f2e18bdcba578c6246", "voter": "0x64d7052676ed4f332c743fD9662ed63eC23edDE8", "created": 1636874638, "choice": 1, "space": {"id": "godboy.eth"}}]}