{"id": "0x2561b120c9ffb93a9541b8450c478336b4ef0c63dca6abaf4a7aff8ee33563a0", "title": "Early Access Alpha", "body": "Who should have access to the early access alpha releases for testing and community development purposes?", "choices": ["Public Access", "Discord Members", "CryptoWeebs / CryptoGFs holders", "Limited Sign Up"], "start": 1635681600, "end": 1636286400, "type": "single-choice", "scores": [0, 0, 0, 0], "scores_total": 0, "scores_state": "final", "scores_updated": 1636759976, "snapshot": "13524408", "state": "closed", "author": "0x6c1Fb499c31aedCE4c535D250993fe25859f5823", "space": {"id": "worldwidewebb.eth", "name": "WORLDWIDE WEBB"}, "votes": 0, "votes_data": []}