{"id": "0x6a8c1d14445c2632e521860b9b93ed239b9b53c940636a5579fe8da780bc4e50", "title": "Can our project market value rank in the top 100?", "body": "", "choices": ["yes", "no"], "start": 1638417600, "end": 1638504000, "type": "single-choice", "scores": [0, 0], "scores_total": 0, "scores_state": "final", "scores_updated": 1638504028, "snapshot": "22044762", "state": "closed", "author": "0xcfA14416Ff1fE2406B7C4903b4E77867F8cC25ff", "space": {"id": "wisereader.eth", "name": "wisereader"}, "votes": 0, "votes_data": []}