{"id": "0xd5c84baafc876f5b21aa4142dc94fb9e31c6af7127403bf6b45fe03208e1a10a", "title": "TEst", "body": "\n**Proposal for:** [Token name]\n\n[A one-line description of the token]\n\n### Technical details\n\n- **Token Name:** [Token name + symbol]\n- **Token Address:** [Token address]\n- **Token Type:** [Token, NFT, Other]\n- **Token Chain** [Binance Smart Chain, Ethereum]\n- **Other:** [If chosen other, otherwise remove]\n- **Stage:** [Announced, Private sale, Pre-sale, Launched, or other]\n- **Link to the whitepaper:** [Link]\n- **Team doxxed:** [Yes/No]\n- **Proof of dox:** [Link]\n- **Smart contract public:** [Yes/no]\n- **Audit:** [Yes/No]\n- **Proof of Audit:** [Link]\n- **LP Lock:** [Yes/No]\n- **LP Lock proof:** [Link]\n\n### Functional details\n\nA brief explanation of the use-case of the underlying project. What is project about? What stage of development are they in? What are important milestones of the project? Do they have important partnerships? etc.\n\n## Fund allocation and personal opinion\n\nIn this section write on why we should vote in favour of your proposal, this is fully limited to your own creativity. Please explain why DCIP should invest in this token, talk about a strategy, will it be long term or short term oriented? Do you have a cashout plan in mind or do you want to discuss this with the community? Or maybe have a TA or other in-depth analysis available please attach them to this proposal.\n    ", "choices": ["Disagree", "Allocate $ 5,670 USD", "Allocate $ 8,505 USD", "Allocate $ 11,340 USD"], "start": 1637060543, "end": 1637622000, "type": "single-choice", "scores": [0, 0, 151160390923.8544, 0], "scores_total": 151160390923.8544, "scores_state": "final", "scores_updated": 1637622018, "snapshot": "14162259", "state": "closed", "author": "0x26Eab0cf20831Cd321b0BFed50A4f93ACA718940", "space": {"id": "beta.dcip.eth", "name": "Random"}, "votes": 1, "votes_data": [{"id": "0x43b577ccad4782f08e6861e6d141470cf6d6b190f5be2d9b2940bcec7c517d6d", "voter": "0x26Eab0cf20831Cd321b0BFed50A4f93ACA718940", "created": 1637060600, "choice": 3, "space": {"id": "beta.dcip.eth"}}]}