{"id": "0x97b2a2f99f83eaab3e2d945d93a55e31c8ee65196c094d1ef5923a67d2368343", "title": "\u4e2d\u5348\u5403\u4ec0\u4e48 \uff1f", "body": "\u5343\u53e4\u96be\u9898", "choices": ["\u76d2\u996d", "\u997a\u5b50", "\u7f8a\u6c64", "\u9ebb\u8fa3\u70eb", "\u725b\u8089\u9762"], "start": 1636344000, "end": 1636516800, "type": "single-choice", "scores": [0, 0, 0, 0, 0], "scores_total": 0, "scores_state": "final", "scores_updated": 1636755781, "snapshot": "21405111", "state": "closed", "author": "0xE7DA5e42a550646fA0A88421A334a982D82D2404", "space": {"id": "arrebol.eth", "name": "Peak DAO"}, "votes": 0, "votes_data": []}