{"id": "0x9b61c211ff8a7e809c5bb4871a9acbd93a391bdc239de386babc1683afe68957", "title": "Should we hire more volunteers to promote our project?", "body": "", "choices": ["yes", "no"], "start": 1638417600, "end": 1638504000, "type": "single-choice", "scores": [0, 0], "scores_total": 0, "scores_state": "final", "scores_updated": 1638504033, "snapshot": "22033020", "state": "closed", "author": "0x6e47A8Df7959C7fDf5A296418FcAA96f677e5960", "space": {"id": "daogov.eth", "name": "SmartDAO"}, "votes": 0, "votes_data": []}