{"id": "0xd1247f677fac6fa831a389fb5e7cf1d555288dd45cfe3f218043491279b8bf2d", "title": "Michael Jackson", "body": "IP Objective: Michael Jackson\nMinimum Fund Raising Target: 1000\nMaximum Fund Raising Target: 50000\nStake Pool Start Date: 2021.11.24  22:00\nStake Pool End Time: 2021.12.04  16:25\n\nMichael Joseph Jackson (August 29, 1958 \u2013 June 25, 2009) was an American singer, songwriter and dancer. Dubbed the \"King of Pop\", he is regarded as one of the most significant cultural figures of the 20th century. Over a four-decade career, his contributions to music, dance and fashion, along with his publicized personal life, made him a global figure in popular culture. Jackson influenced artists across many music genres; through stage and video performances, he popularized complicated dance moves such as the moonwalk, to which he gave the name, as well as the robot. He is the most awarded music artist in history.", "choices": ["Yes", "No"], "start": 1637787600, "end": 1638635400, "type": "single-choice", "scores": [41.853626619543334, 0], "scores_total": 41.853626619543334, "scores_state": "final", "scores_updated": 1638635430, "snapshot": "13191961", "state": "closed", "author": "0x9c32555C64879004AC20a2192557eC48a2e4b807", "space": {"id": "pizzap.eth", "name": "Pizzap"}, "votes": 1, "votes_data": [{"id": "0x2dad795377d2cb2dce510b3042df1e7c00af87caf064867c9d0e275031636e12", "voter": "0x9c32555C64879004AC20a2192557eC48a2e4b807", "created": 1638635191, "choice": 1, "space": {"id": "pizzap.eth"}}]}