{"id": "0x77bc179b2c95186805f88e95bdcdcf65157be6772100186866fca16db0ef64c9", "title": "balldao", "body": "This is a ball voting community, supported by the cryptocurrency shib token, do you see shib participating in various ball tournaments in the coming years, intermingling with real life.", "choices": ["yes", "no"], "start": 1639195200, "end": 1639800000, "type": "single-choice", "scores": [105506063.26666407, 0], "scores_total": 105506063.26666407, "scores_state": "final", "scores_updated": 1639800038, "snapshot": "13783210", "state": "closed", "author": "0x04e4F47e79B9B1A66f736b6797fE13F25e581C11", "space": {"id": "balldao.eth", "name": "tai"}, "votes": 1, "votes_data": [{"id": "0xafbcf1fea08896762d5522f7df2accfd2b9f24188353946ce6ecba420a9359cc", "voter": "0x04e4F47e79B9B1A66f736b6797fE13F25e581C11", "created": 1639217330, "choice": 1, "space": {"id": "balldao.eth"}}]}