{"id": "0xdac3dcebcc775879112e490abc2230e8c283a946d8b27bbf048f3add70c1f4ed", "title": "bitcoin to the moon?", "body": "", "choices": ["yes", "no"], "start": 1637704800, "end": 1638244800, "type": "single-choice", "scores": [293.88622551526055, 0], "scores_total": 293.88622551526055, "scores_state": "final", "scores_updated": 1638245460, "snapshot": "12907277", "state": "closed", "author": "0xE3448A009cd7f6adCE7c521c521DD75472cb9d0c", "space": {"id": "partchyan.eth", "name": "ONEBORINGSPACE-DAO"}, "votes": 1, "votes_data": [{"id": "0x0ac9b333c62014eb3342efeaf3d83e73c439e114f702ac004ee111010ee00401", "voter": "0x631AE5539Ca9E8CC1C16dC256F913C6f5366D84e", "created": 1638002957, "choice": 1, "space": {"id": "partchyan.eth"}}]}