{"id": "0xb212994e3c091787439ca6e39221aaba4f658242ca481c13b457be44b07d5a16", "title": "snapshot\u4f1a\u53d1\u5e01\u5417", "body": "\u4f1a", "choices": ["yes", "no"], "start": 1637487891, "end": 1637505891, "type": "single-choice", "scores": [0, 0], "scores_total": 0, "scores_state": "final", "scores_updated": 1637505900, "snapshot": "13651189", "state": "closed", "author": "0x5071E1944D0B318461736B8d6118307853448ed8", "space": {"id": "000666.eth", "name": "\u5929\u6210588"}, "votes": 0, "votes_data": []}